flastik/LICENSE.txt
flastik/README.pdf
flastik/__init__.py
flastik/flastik.py
flastik/base_templates/base.html
flastik/base_templates/default_icon.png
flastik/base_templates/footer.html
flastik/base_templates/hello_world.html
flastik/base_templates/navbar.html
flastik/base_templates/stylesheet.css
flastik/base_templates/test.html
flastik/bootstrap/css/bootstrap-grid.css
flastik/bootstrap/css/bootstrap-grid.css.map
flastik/bootstrap/css/bootstrap-grid.min.css
flastik/bootstrap/css/bootstrap-grid.min.css.map
flastik/bootstrap/css/bootstrap-reboot.css
flastik/bootstrap/css/bootstrap-reboot.css.map
flastik/bootstrap/css/bootstrap-reboot.min.css
flastik/bootstrap/css/bootstrap-reboot.min.css.map
flastik/bootstrap/css/bootstrap.css
flastik/bootstrap/css/bootstrap.css.map
flastik/bootstrap/css/bootstrap.min.css
flastik/bootstrap/css/bootstrap.min.css.map
flastik/bootstrap/jquery/jquery-3.4.1.min.js
flastik/bootstrap/js/bootstrap.bundle.js
flastik/bootstrap/js/bootstrap.bundle.js.map
flastik/bootstrap/js/bootstrap.bundle.min.js
flastik/bootstrap/js/bootstrap.bundle.min.js.map
flastik/bootstrap/js/bootstrap.js
flastik/bootstrap/js/bootstrap.js.map
flastik/bootstrap/js/bootstrap.min.js
flastik/bootstrap/js/bootstrap.min.js.map
flastik/bootstrap/popper/popper.min.js
flastik/doc_templates/classes_page.html
flastik/doc_templates/functions_page.html
flastik/doc_templates/home_page.html
flastik/doc_templates/navbar.html
flastik-1.0.2.data/scripts/flastik
flastik-1.0.2.dist-info/LICENSE
flastik-1.0.2.dist-info/METADATA
flastik-1.0.2.dist-info/WHEEL
flastik-1.0.2.dist-info/top_level.txt
flastik-1.0.2.dist-info/RECORD
