Metadata-Version: 2.1
Name: flastik
Version: 1.0.2
Summary: A Flask-like Tiny-framework for static websites
Home-page: UNKNOWN
Author: Dr. Thomas Roc
Author-email: info@electricbrain.fr
License: UNKNOWN
Platform: UNKNOWN
Requires-Python: >=3.6
Requires-Dist: jinja2
Requires-Dist: docutils
Requires-Dist: pytest
